accesomongo/__init__.py
accesomongo/pandasmongodb.py
accesomongo-1.0.dist-info/METADATA
accesomongo-1.0.dist-info/WHEEL
accesomongo-1.0.dist-info/top_level.txt
accesomongo-1.0.dist-info/RECORD
