Metadata-Version: 2.1
Name: accesomongo
Version: 1.0
Summary: Funciones basadas en Pandas, para acceder a MongoDB, local o MongoDB Atlas
Home-page: https://dina.concytec.gob.pe/appDirectorioCTI/VerDatosInvestigador.do?id_investigador=12581
Author: Jorge Guerra Guerra
Author-email: jguerra91@gmail.com
License: UNKNOWN
Platform: UNKNOWN
